geosite/__init__.py
geosite/giserpy.cpython-310-darwin.so
geosite/MapGIS/Slib/Pcolor.lib
giserpy-2025.9.10.dist-info/METADATA
giserpy-2025.9.10.dist-info/WHEEL
giserpy-2025.9.10.dist-info/top_level.txt
giserpy-2025.9.10.dist-info/RECORD
