Metadata-Version: 2.4
Name: giserpy
Version: 2025.9.10
Summary: 主要模块包括： Messenger - 信使消息事件订阅与发布类； MapGisProject - MapGis工程文件（MPJ）读取类； MapGisColorLib - MapGis色库（青品黄黑-红绿蓝）读取类； MapGisFile - MapGis点线面文件读取类； Projection - 几何要素坐标投影变换类； MapGrid - 国际标准比例尺图幅分幅网格与编号类；Geometry - 地学几何要素加载、编码、转换与序列化类
Home-page: http://www.xacgs.cn
Author: Geosite Development Team of CGS
Keywords: MapGIS,Projection,MapGrid,Geometry
Requires-Python: >=3.9
Dynamic: author
Dynamic: description
Dynamic: description-content-type
Dynamic: home-page
Dynamic: keywords
Dynamic: requires-python
Dynamic: summary
